taskvine_report/__init__.py
taskvine_report/cli/__init__.py
taskvine_report/cli/parse.py
taskvine_report/cli/report.py
taskvine_report/routes/__init__.py
taskvine_report/routes/file_concurrent_replicas.py
taskvine_report/routes/file_created_size.py
taskvine_report/routes/file_retention_time.py
taskvine_report/routes/file_sizes.py
taskvine_report/routes/file_transferred_size.py
taskvine_report/routes/lock.py
taskvine_report/routes/logger.py
taskvine_report/routes/runtime_state.py
taskvine_report/routes/runtime_template.py
taskvine_report/routes/task_completion_percentiles.py
taskvine_report/routes/task_concurrency.py
taskvine_report/routes/task_dependencies.py
taskvine_report/routes/task_dependents.py
taskvine_report/routes/task_execution_details.py
taskvine_report/routes/task_execution_time.py
taskvine_report/routes/task_response_time.py
taskvine_report/routes/task_retrieval_time.py
taskvine_report/routes/task_subgraphs.py
taskvine_report/routes/utils.py
taskvine_report/routes/worker_concurrency.py
taskvine_report/routes/worker_executing_tasks.py
taskvine_report/routes/worker_lifetime.py
taskvine_report/routes/worker_storage_consumption.py
taskvine_report/routes/worker_transfers.py
taskvine_report/routes/worker_waiting_retrieval_tasks.py
taskvine_report/src/__init__.py
taskvine_report/src/data_parse.py
taskvine_report/src/file_info.py
taskvine_report/src/logger.py
taskvine_report/src/manager_info.py
taskvine_report/src/task_info.py
taskvine_report/src/utils.py
taskvine_report/src/worker_info.py
taskvine_report/static/favicon.ico
taskvine_report/static/css/content.css
taskvine_report/static/css/header.css
taskvine_report/static/css/legend.css
taskvine_report/static/css/logtext.css
taskvine_report/static/css/report.css
taskvine_report/static/css/section.css
taskvine_report/static/css/sidebar.css
taskvine_report/static/css/support.css
taskvine_report/static/css/tables.css
taskvine_report/static/css/toolbox.css
taskvine_report/static/imgs/taskvine_icon.svg
taskvine_report-3.0.0.dist-info/METADATA
taskvine_report-3.0.0.dist-info/WHEEL
taskvine_report-3.0.0.dist-info/entry_points.txt
taskvine_report-3.0.0.dist-info/top_level.txt
taskvine_report-3.0.0.dist-info/RECORD
