Metadata-Version: 2.1
Name: taskvine-report
Version: 3.0.0
Summary: Visualization and analysis tool for TaskVine execution logs
Home-page: https://github.com/cooperative-computing-lab/taskvine-report-tool
Author: Collaborative Computing Lab (CCL), University of Notre Dame
Author-email: jzhou24@nd.edu
Project-URL: Bug Reports, https://github.com/cooperative-computing-lab/taskvine-report-tool/issues
Project-URL: Source, https://github.com/cooperative-computing-lab/taskvine-report-tool
Project-URL: Documentation, https://ccl.cse.nd.edu/software/taskvine/
Project-URL: CCL Homepage, https://ccl.cse.nd.edu/
Keywords: taskvine,workflow,visualization,monitoring,distributed-computing,ccl,notre-dame
Classifier: Development Status :: 4 - Beta
Classifier: Intended Audience :: Developers
Classifier: Intended Audience :: Science/Research
Classifier: License :: OSI Approved :: MIT License
Classifier: Operating System :: OS Independent
Classifier: Programming Language :: Python :: 3
Classifier: Programming Language :: Python :: 3.7
Classifier: Programming Language :: Python :: 3.8
Classifier: Programming Language :: Python :: 3.9
Classifier: Programming Language :: Python :: 3.10
Classifier: Programming Language :: Python :: 3.11
Classifier: Topic :: Scientific/Engineering
Classifier: Topic :: System :: Distributed Computing
Classifier: Topic :: System :: Monitoring
Requires-Python: >=3.7
Requires-Dist: flask>=2.0.0
Requires-Dist: pandas>=1.3.0
Requires-Dist: cloudpickle>=2.0.0
Requires-Dist: tqdm>=4.60.0
Requires-Dist: bitarray>=2.0.0
Requires-Dist: pytz>=2021.1
Requires-Dist: graphviz>=0.17
Provides-Extra: dev
Requires-Dist: pytest>=6.0; extra == "dev"
Requires-Dist: pytest-cov>=2.0; extra == "dev"
Requires-Dist: black>=21.0; extra == "dev"
Requires-Dist: flake8>=3.8; extra == "dev"
Requires-Dist: mypy>=0.800; extra == "dev"
Provides-Extra: test
Requires-Dist: pytest>=6.0; extra == "test"
Requires-Dist: pytest-cov>=2.0; extra == "test"
